data/__about__.py
data/__init__.py
data/contents.py
data/generators.py
data/signals.py
data/tests.py
pelican_data-0.2.0.dist-info/LICENSE
pelican_data-0.2.0.dist-info/METADATA
pelican_data-0.2.0.dist-info/WHEEL
pelican_data-0.2.0.dist-info/top_level.txt
pelican_data-0.2.0.dist-info/RECORD
