Metadata-Version: 1.2
Name: pelican-data
Version: 0.2.0
Summary: Data and collections for Pelican
Home-page: https://github.com/noirbizarre/pelican-data
Author: Axel Haustant
Author-email: noirbizarre+github@gmail.com
License: MIT
Keywords: pelican,data,yaml
Platform: UNKNOWN
Classifier: Development Status :: 3 - Alpha
Classifier: Programming Language :: Python
Classifier: Environment :: Web Environment
Classifier: Operating System :: OS Independent
Classifier: Intended Audience :: Developers
Classifier: Topic :: System :: Software Distribution
Classifier: Programming Language :: Python
Classifier: Programming Language :: Python :: 3
Classifier: Programming Language :: Python :: 3.6
Classifier: Programming Language :: Python :: 3.7
Classifier: Programming Language :: Python :: 3.8
Classifier: Topic :: Software Development :: Libraries :: Python Modules
Classifier: License :: OSI Approved :: MIT License
Requires-Python: >=3.6
